[
  {
    "id": 1,
    "query": "放課後等デイサービスとは 対象年齢と利用条件",
    "status": "todo"
  },
  {
    "id": 2,
    "query": "受給者証の取得方法と申請の流れ",
    "status": "todo"
  },
  {
    "id": 3,
    "query": "放課後等デイサービスの選び方 チェックリスト",
    "status": "todo"
  },
  {
    "id": 4,
    "query": "見学時に確認すべきポイント",
    "status": "todo"
  },
  {
    "id": 5,
    "query": "利用料金の仕組みと自己負担上限月額",
    "status": "todo"
  },
  {
    "id": 6,
    "query": "児童発達支援と放課後等デイサービスの違い",
    "status": "todo"
  },
  {
    "id": 7,
    "query": "送迎サービスの有無で選ぶポイント",
    "status": "todo"
  },
  {
    "id": 8,
    "query": "学校との連携はどうなっているか",
    "status": "todo"
  },
  {
    "id": 9,
    "query": "個別支援計画とは何か",
    "status": "todo"
  },
  {
    "id": 10,
    "query": "事業所を変更したいときの手続き",
    "status": "todo"
  }
]